rtl/slave_interface.v
module slave_interface	(	input pclk,
				input preset,
				input psel,
				input penable,
				input pwrite,
				output pready,
				input [31:0] pwdata,
				input [3:0] paddr,
				output reg [31:0] prdata,
				output irq,
				output sys_clk,
				output sys_rst,
				output reg gpio_we,
				output [3:0] gpio_addr,
				output reg [31:0] gpio_dat_i,
				input [31:0] gpio_dat_o,
				input gpio_inta_o
			);

	
	parameter idle = 2'd0;
	parameter setup = 2'd1;
	parameter enable = 2'd2;
	
	reg [1:0] pres, next;
	
	assign irq = gpio_inta_o;
	assign gpio_addr = paddr;
	assign sys_rst = preset;
	assign sys_clk = pclk;
	
	assign pready = ( (pres == enable) || (pres == idle && preset == 1'b1) ) ? 1'b1: 1'b0;
	
	always @ (posedge pclk or posedge preset)
	begin
		if (preset == 1'b1)
			pres <= idle;
		else
			pres <= next;
	end
	
	always @ (*)
	begin
		case(pres)
			idle:	begin
					if(psel == 1'b1 && penable == 1'b0)
						next = setup;
					else
						next = idle;
				end
			
			setup:	begin
					if(psel == 1'b1 && penable == 1'b1)
						next = enable;
					else if(psel == 1'b1 && penable == 1'b0)
						next = setup;
					else
						next = idle;
				end
				
			enable:	begin
					if(psel == 1'b1)
						next = setup;
					else
						next = idle;
				end
			
			default: next = idle;	
		endcase
	end
	
	
	always @ (*)
	begin
		if(pres == enable && pwrite == 1'b1)
		begin
			gpio_dat_i = pwdata;
			gpio_we = 1'b1;
			prdata = 32'd0;
		end
		
		else if(pres == enable && pwrite == 1'b0)
		begin
			gpio_dat_i = 32'd0;
			gpio_we = 1'b0;
			prdata = gpio_dat_o;
		end
		
		else
		begin
			gpio_dat_i = 32'd0;
			gpio_we = 1'b0;
			prdata = 32'd0;
		end
	end
	
endmodule

tb/slave_interface_tb.v
module slave_interface_tb;
	reg pclk, preset, psel, penable, pwrite, gpio_inta_o;
	reg [31:0] pwdata, gpio_dat_o;
	reg [3:0] paddr;
	wire pready, irq, sys_clk, sys_rst, gpio_we;
	wire [3:0] gpio_addr;
	wire [31:0] prdata, gpio_dat_i;
	
	slave_interface DUT (	.pclk(pclk),
				.preset(preset),
				.psel(psel),
				.penable(penable),
				.pwrite(pwrite),
				.pready(pready),
				.pwdata(pwdata),
				.paddr(paddr),
				.prdata(prdata),
				.irq(irq),
				.sys_clk(sys_clk),
				.sys_rst(sys_rst),
				.gpio_we(gpio_we),
				.gpio_addr(gpio_addr),
				.gpio_dat_i(gpio_dat_i),
				.gpio_dat_o(gpio_dat_o),
				.gpio_inta_o(gpio_inta_o)	);
				
	initial
	begin
		pclk = 1'b0;
		psel = 1'b0;
		penable = 1'b0;
		pwrite = 1'b0;
	end
	
	always #5 pclk = ~pclk;

    always @ (posedge pclk) 
	begin
	
	if(preset == 1'b1)
		gpio_dat_o <= 32'd0;
	
        else if(gpio_we == 1'b1) 
	begin
            gpio_dat_o <= gpio_dat_i;
        end
    end
	
	initial
	begin
	
		//-------------------write cycle-----------------------
		
		preset = 1'b1;
		#10 preset = 1'b0;
		
		@(negedge pclk);
			paddr = 4'd2;
			pwrite = 1'b1;
			pwdata = 32'd17;
			psel = 1'b1;
		
		@(negedge pclk);
			penable = 1'b1;
			
		@(negedge pclk);
			while(pready == 1'b0)
				@(negedge pclk);
		
			penable = 1'b0;
			psel = 1'b0;

		//--------------------read cycle-----------------------
		
		@(negedge pclk);
		    paddr = 4'd2;
		    pwrite = 1'b0;
		    psel = 1'b1;
		
		@(negedge pclk);
		    penable = 1'b1;

		@(negedge pclk);
			while(pready == 1'b0)
				@(negedge pclk);
	
			penable = 1'b0;
			psel = 1'b0;
			
		//-------------------------------------------------------
		
		#100 $finish;
		
	end
		
	initial 
	begin
		$dumpfile("apb_slave.vcd"); 
		$dumpvars(0, slave_interface_tb);
	end
	
endmodule

sim/apb_slave.vcd
$date
	Wed May 20 17:09:14 2026
$end
$version
	Icarus Verilog
$end
$timescale
	1s
$end
$scope module slave_interface_tb $end
$var wire 1 ! sys_rst $end
$var wire 1 " sys_clk $end
$var wire 1 # pready $end
$var wire 32 $ prdata [31:0] $end
$var wire 1 % irq $end
$var wire 1 & gpio_we $end
$var wire 32 ' gpio_dat_i [31:0] $end
$var wire 4 ( gpio_addr [3:0] $end
$var reg 32 ) gpio_dat_o [31:0] $end
$var reg 1 * gpio_inta_o $end
$var reg 4 + paddr [3:0] $end
$var reg 1 , pclk $end
$var reg 1 - penable $end
$var reg 1 . preset $end
$var reg 1 / psel $end
$var reg 32 0 pwdata [31:0] $end
$var reg 1 1 pwrite $end
$scope module DUT $end
$var wire 4 2 gpio_addr [3:0] $end
$var wire 32 3 gpio_dat_o [31:0] $end
$var wire 1 * gpio_inta_o $end
$var wire 1 % irq $end
$var wire 4 4 paddr [3:0] $end
$var wire 1 , pclk $end
$var wire 1 - penable $end
$var wire 1 . preset $end
$var wire 1 / psel $end
$var wire 32 5 pwdata [31:0] $end
$var wire 1 1 pwrite $end
$var wire 1 " sys_clk $end
$var wire 1 ! sys_rst $end
$var wire 1 # pready $end
$var reg 32 6 gpio_dat_i [31:0] $end
$var reg 1 & gpio_we $end
$var reg 2 7 next [1:0] $end
$var reg 32 8 prdata [31:0] $end
$var reg 2 9 pres [1:0] $end
$upscope $end
$upscope $end
$enddefinitions $end
#0
$dumpvars
b0 9
b0 8
b0 7
b0 6
bx 5
bx 4
bx 3
bx 2
01
bx 0
0/
1.
0-
0,
bx +
x*
bx )
bx (
b0 '
0&
x%
b0 $
1#
0"
1!
$end
#5
b0 )
b0 3
1"
1,
#10
0#
b1 7
1/
b10001 0
b10001 5
11
b10 (
b10 2
b10 +
b10 4
0"
0,
0!
0.
#15
b1 9
1"
1,
#20
b10 7
1-
0"
0,
#25
1#
1&
b10001 '
b10001 6
b1 7
b10 9
1"
1,
#30
b0 7
0/
0-
0"
0,
#35
0#
0&
b0 '
b0 6
b0 9
b10001 )
b10001 3
1"
1,
#40
b1 7
1/
01
0"
0,
#45
b1 9
1"
1,
#50
b10 7
1-
0"
0,
#55
1#
b10001 $
b10001 8
b1 7
b10 9
1"
1,
#60
b0 7
0/
0-
0"
0,
#65
0#
b0 $
b0 8
b0 9
1"
1,
