rtl/aux_interface.v
module aux_interface	(
			input clk,
			input rst,
			input [31:0] aux_in,
			output reg [31:0] aux_i
			);
						
	always @ (posedge clk or posedge rst)
	begin
		if(rst == 1'b1)
			aux_i <= 32'd0;
		else
			aux_i <= aux_in;
	end
	
endmodule

tb/aux_interface_tb.v
`timescale 1ns/1ps

module aux_interface_tb;
	reg clk, rst;
	reg [31:0] aux_in;
	wire [31:0] aux_i;
	
	aux_interface DUT (	.clk(clk),
				.rst(rst),
				.aux_in(aux_in),
				.aux_i(aux_i)
			);
	
	initial clk = 1'b0;
	always #5 clk = ~clk;
	
	initial
	begin
		rst = 1'b0;
		aux_in = 32'd0;
		
		@(negedge clk);
			rst = 1'b1;
		@(negedge clk);
			rst = 1'b0;
		
		@(negedge clk);
		@(negedge clk);
			aux_in = 32'habab_abab;
			
		@(negedge clk);
		@(negedge clk);
			aux_in = 32'heffe_feef;
		
		#40 $finish;
	end
	
	initial 
	begin
		$dumpfile("aux_sim.vcd");
		$dumpvars(0, aux_interface_tb);
	end
	
endmodule

sim/aux_sim.vcd
$date
	Thu May 28 17:02:44 2026
$end
$version
	Icarus Verilog
$end
$timescale
	1ps
$end
$scope module aux_interface_tb $end
$var wire 32 ! aux_i [31:0] $end
$var reg 32 " aux_in [31:0] $end
$var reg 1 # clk $end
$var reg 1 $ rst $end
$scope module DUT $end
$var wire 32 % aux_in [31:0] $end
$var wire 1 # clk $end
$var wire 1 $ rst $end
$var reg 32 & aux_i [31:0] $end
$upscope $end
$upscope $end
$enddefinitions $end
#0
$dumpvars
bx &
b0 %
0$
0#
b0 "
bx !
$end
#5000
b0 !
b0 &
1#
#10000
1$
0#
#15000
1#
#20000
0$
0#
#25000
1#
#30000
0#
#35000
1#
#40000
b10101011101010111010101110101011 "
b10101011101010111010101110101011 %
0#
#45000
b10101011101010111010101110101011 !
b10101011101010111010101110101011 &
1#
#50000
0#
#55000
1#
#60000
b11101111111111101111111011101111 "
b11101111111111101111111011101111 %
0#
#65000
b11101111111111101111111011101111 !
b11101111111111101111111011101111 &
1#
