rtl/io_interface.v
module io_interface	(
			input ext_clk_pad_i,
			input [31:0] out_pad_o, 
			input [31:0] oen_padoe_o,
			output [31:0] in_pad_i,
			inout [31:0] io_pad,
			output gpio_eclk
			);
	
	assign in_pad_i = io_pad;
	assign gpio_eclk = ext_clk_pad_i;
	
	genvar i;
	
	generate
		for(i=0; i<32; i=i+1)
		begin: gpio_output_tri_buffers
			assign io_pad[i] = oen_padoe_o[i] ? out_pad_o[i] : 1'bz;
		end
	endgenerate

endmodule

rtl/gpio_register.v
module gpio_register (	input sys_clk,
			input sys_rst,
			input gpio_we,
			input [31:0] gpio_addr,
			input [31:0] gpio_dat_i,
			output reg [31:0] gpio_dat_o,
			output gpio_inta_o,
			input [31:0] aux_i,
			input [31:0] in_pad_i,
			input gpio_eclk,
			output [31:0] out_pad_o,
			output [31:0] oen_padoe_o
			);

	
	parameter addr_rgpio_in = 32'h00;
	parameter addr_rgpio_out = 32'h04;
	parameter addr_rgpio_oe = 32'h08;
	parameter addr_rgpio_inte = 32'h0c;
	parameter addr_rgpio_ptrig = 32'h10;
	parameter addr_rgpio_aux = 32'h14;
	parameter addr_rgpio_ctrl = 32'h18;
	parameter addr_rgpio_ints = 32'h1c;
	parameter addr_rgpio_eclk = 32'h20;
	parameter addr_rgpio_nec = 32'h24;
	
	parameter addr_rgpio_ctrl_inte = 0;
	parameter addr_rgpio_ctrl_ints = 1;
	
	reg [31:0] rgpio_in, rgpio_out, rgpio_oe, rgpio_inte, rgpio_ptrig, rgpio_aux, rgpio_ctrl, rgpio_ints, rgpio_eclk, rgpio_nec;
	reg [1:0]  rgpio_ctrl;
	
	reg [31:0] dat_reg;				//used to hold output, we use this to send to gpio_dat_o reg on posedge of sys clk
	
	wire [31:0] extclk_in;				//multiplexed inputs by ext clk
	reg [31:0] pextc_sampled, nextc_sampled;	//posedge and negedge ext clk sampled inputs
	
	//--------------------------------------
	
	//gpio ctrl logic block
	
	always @ (posedge sys_clk or posedge sys_rst)
		if(sys_rst == 1'b1)
			rgpio_ctrl <= 2'd0;
		else if( (gpio_addr == addr_rgpio_ctrl) && gpio_we == 1'b1 )					//if addr is of gpio ctrl reg and wr en is high
			rgpio_ctrl <= gpio_dat_i[1:0];								//assign lsb 2 bits of input stream to ctrl reg
		else if(rgpio_ctrl[addr_rgpio_ctrl_inte] == 1'b1)						//if interrupts enabled
			rgpio_ctrl[addr_rgpio_ctrl_ints] <= rgpio_ctrl[addr_rgpio_ctrl_ints] | gpio_inta_o;	//update status reg and keep it high until serviced
	
	//--------------------------------------
	
	//gpio out logic block
	
	always @ (posedge sys_clk or posedge sys_rst)
		if(sys_rst == 1'b1)
			rgpio_out <= 32'd0;
		else if( (gpio_addr == addr_rgpio_out) && gpio_we == 1'b1 )
			rgpio_out <= gpio_dat_i[31:0];
		else
			rgpio_out <= rgpio_out;
			
	//--------------------------------------
	
	//gpio output enable logic block
	
	always @ (posedge sys_clk or posedge sys_rst)
		if(sys_rst == 1'b1)
			rgpio_oe <= 32'd0;
		else if( (gpio_addr == addr_rgpio_oe) && gpio_we == 1'b1 )
			rgpio_oe <= gpio_dat_i[31:0];
		else
			rgpio_oe <= rgpio_oe;		//extra line added, if bug remove
			
	//--------------------------------------
	
	//gpio interrupt enable
	
	always @ (posedge sys_clk or posedge sys_rst)
		if(sys_rst == 1'b1)
			rgpio_inte <= 32'd0;
		else if( (gpio_addr == addr_rgpio_inte) && gpio_we == 1'b1 )
			rgpio_inte <= gpio_dat_i[31:0];
		else
			rgpio_inte <= rgpio_inte;
	
	//--------------------------------------
	
	//gpio posedge trigger register
	
	always @ (posedge sys_clk or posedge sys_rst)
		if(sys_rst == 1'b1)
			rgpio_ptrig <= 32'd0;
		else if( (gpio_addr == addr_rgpio_ptrig) && gpio_we == 1'b1 )
			rgpio_ptrig <= gpio_dat_i[31:0];
		else
			rgpio_ptrig <= rgpio_ptrig;
		
	//--------------------------------------
	
	//gpio aux register
	
	always @ (posedge sys_clk or posedge sys_rst)
		if(sys_rst == 1'b1)
			rgpio_aux <= 32'd0;
		else if( (gpio_addr == addr_rgpio_aux) && gpio_we == 1'b1 )
			rgpio_aux <= gpio_dat_i[31:0];
		else
			rgpio_aux <= rgpio_aux;
			
	//--------------------------------------
	
	//gpio ext clk register
	
	always @ (posedge sys_clk or posedge sys_rst)
		if(sys_rst == 1'b1)
			rgpio_eclk <= 32'd0;
		else if( (gpio_addr == addr_rgpio_eclk) && gpio_we == 1'b1 )
			rgpio_eclk <= gpio_dat_i[31:0];
		else
			rgpio_eclk <= rgpio_eclk;
		
	//--------------------------------------
	
	//neg edge ext clk register
	
	always @ (posedge sys_clk or posedge sys_rst)
		if(sys_rst == 1'b1)
			rgpio_nec <= 32'd0;
		else if( (gpio_addr == addr_rgpio_nec) && gpio_we == 1'b1)
			rgpio_nec <= gpio_dat_i[31:0];
		else
			rgpio_nec <= rgpio_nec;
			
	//--------------------------------------
	
	//sending input to gpio in reg
	
	wire [31:0] muxed_in;
	
	always @ (posedge sys_clk or posedge sys_rst)
		if(sys_rst == 1'b1)
			rgpio_in <= 32'd0;
		else
			rgpio_in <= muxed_in;
	
	assign muxed_in = (rgpio_eclk & extclk_in) | (~rgpio_eclk & in_pad_i);		//if ext clk reg high, then pass ext clk, if not, pass input from input pad
	
	assign extclk_in = (~rgpio_nec & pextc_sampled) | (rgpio_nec & nextc_sampled);	//if neg edge reg low, then pass posedge sampled input, if high, then pass negedge sampled input
	
	//--------------------------------------
	
	//posedge sampled input, note the use of ext clk here
	
	always @ (posedge gpio_eclk or posedge sys_rst)
		if(sys_rst == 1'b1)
			pextc_sampled <= 32'd0;
		else
			pextc_sampled <= in_pad_i;
	
	//negedge sampled input, note ext clk
	
	always @ (negedge gpio_eclk or posedge sys_rst)
		if(sys_rst == 1'b1)
			nextc_sampled <= 32'd0;
		else
			nextc_sampled <= in_pad_i;
	
	//--------------------------------------
	
	//passing register contents to intermediate signal
	
	always @ (*)
		case(gpio_addr)
			addr_rgpio_out: dat_reg = rgpio_out;
			addr_rgpio_oe: dat_reg = rgpio_oe;
			addr_rgpio_inte: dat_reg = rgpio_inte;
			addr_rgpio_ptrig: dat_reg = rgpio_ptrig;
			addr_rgpio_nec: dat_reg = rgpio_nec;
			addr_rgpio_eclk: dat_reg = rgpio_eclk;
			addr_rgpio_aux: dat_reg = rgpio_aux;
			addr_rgpio_ctrl:	begin
							dat_reg[1:0] = rgpio_ctrl;
							dat_reg[31:2] = 30'd0;
						end
			addr_rgpio_ints: dat_reg = rgpio_ints;
			default: dat_reg = rgpio_in;
		endcase
		
	//--------------------------------------
	
	//passing intermediate signal value to gpio output reg
	
	always @ (posedge sys_clk or posedge sys_rst)
		if(sys_rst == 1'b1)
			gpio_dat_o <= 32'd0;
		else
			gpio_dat_o <= dat_reg;

	//--------------------------------------
	
	//gpio interrupt status reg, wr and rd 
	
	always @ (posedge sys_clk or posedge sys_rst)
		if(sys_rst == 1'b1)
			rgpio_ints <= 32'd0;
		else if( (gpio_addr == addr_rgpio_ints) && gpio_we == 1'b1 )
			rgpio_ints <= gpio_dat_i;
		else if(rgpio_ctrl[addr_rgpio_ctrl_inte] == 1'b1)
			rgpio_ints <= (rgpio_ints | ((muxed_in ^ rgpio_in) & ~(muxed_in ^ rgpio_ptrig)) & rgpio_inte);
	
	//--------------------------------------
	
	assign gpio_inta_o = |rgpio_ints ? rgpio_ctrl[addr_rgpio_ctrl_inte] : 1'b0;		//gen interrupt req, note the use of the 'reduction or'	operator
	assign oen_padoe_o = rgpio_oe;								//output enables are the same as gpio output enable register bits
	assign out_pad_o = (rgpio_out & ~rgpio_aux) | (aux_i & rgpio_aux);			//generate gpio output as register output if no aux input, if aux input present, pass that as output
	
endmodule

rtl/aux_interface.v
module aux_interface	(
			input clk,
			input rst,
			input [31:0] aux_in,
			output reg [31:0] aux_i
			);
						
	always @ (posedge clk or posedge rst)
	begin
		if(rst == 1'b1)
			aux_i <= 32'd0;
		else
			aux_i <= aux_in;
	end
	
endmodule

rtl/slave_interface.v
module slave_interface	(	input pclk,
				input preset,
				input psel,
				input penable,
				input pwrite,
				output pready,
				input [31:0] pwdata,
				input [31:0] paddr,
				output reg [31:0] prdata,
				output irq,
				output sys_clk,
				output sys_rst,
				output reg gpio_we,
				output [31:0] gpio_addr,
				output reg [31:0] gpio_dat_i,
				input [31:0] gpio_dat_o,
				input gpio_inta_o
			);

	
	parameter idle = 2'd0;
	parameter setup = 2'd1;
	parameter enable = 2'd2;
	
	reg [1:0] pres, next;
	
	assign irq = gpio_inta_o;
	assign gpio_addr = paddr;
	assign sys_rst = preset;
	assign sys_clk = pclk;
	
	assign pready = ( (pres == enable) || (pres == idle && preset == 1'b1) ) ? 1'b1: 1'b0;
	
	always @ (posedge pclk or posedge preset)
	begin
		if (preset == 1'b1)
			pres <= idle;
		else
			pres <= next;
	end
	
	always @ (*)
	begin
		case(pres)
			idle:	begin
					if(psel == 1'b1 && penable == 1'b0)
						next = setup;
					else
						next = idle;
				end
			
			setup:	begin
					if(psel == 1'b1 && penable == 1'b1)
						next = enable;
					else if(psel == 1'b1 && penable == 1'b0)
						next = setup;
					else
						next = idle;
				end
				
			enable:	begin
					if(psel == 1'b1)
						next = setup;
					else
						next = idle;
				end
			
			default: next = idle;	
		endcase
	end
	
	
	always @ (*)
	begin
		if(pres == enable && pwrite == 1'b1)
		begin
			gpio_dat_i = pwdata;
			gpio_we = 1'b1;
			prdata = 32'd0;
		end
		
		else if(pres == enable && pwrite == 1'b0)
		begin
			gpio_dat_i = 32'd0;
			gpio_we = 1'b0;
			prdata = gpio_dat_o;
		end
		
		else
		begin
			gpio_dat_i = 32'd0;
			gpio_we = 1'b0;
			prdata = 32'd0;
		end
	end
	
endmodule

rtl/gpio_top.v
module gpio_top	(	
		input pclk,
		input preset,
		output [31:0] prdata,
		input [31:0] paddr,
		input [31:0] pwdata,
		input psel,
		input penable,
		input pwrite,
		input [31:0] aux_in,
		output irq,
		output pready,
		inout [31:0] io_pad,
		input ext_clk_pad_i
		);
					
	wire [31:0] in_pad_i;
	wire gpio_we;
	wire [31:0] gpio_addr;
	wire [31:0] gpio_dat_i;
	wire [31:0] gpio_dat_o;
	wire [31:0] out_pad_o;
	wire [31:0] oen_padoe_o;
	wire gpio_inta_o;
	wire sys_clk;
	wire sys_rst;
	wire [31:0] aux_i;
	wire ext_clk_to_gpio_eclk;
	
	slave_interface slv_intf	(	
					.pclk(pclk),
					.preset(preset),
					.psel(psel),
					.penable(penable),
					.pwrite(pwrite),
					.pready(pready),
					.pwdata(pwdata),
					.paddr(paddr),
					.prdata(prdata),
					.irq(irq),
					.sys_clk(sys_clk),
					.sys_rst(sys_rst),
					.gpio_we(gpio_we),
					.gpio_addr(gpio_addr),
					.gpio_dat_i(gpio_dat_i),
					.gpio_dat_o(gpio_dat_o),
					.gpio_inta_o(gpio_inta_o)
					);
	
	
	aux_interface	aux_intf	(	
					.clk(sys_clk),
					.rst(sys_rst),
					.aux_in(aux_in),
					.aux_i(aux_i)
					);
					
	
	gpio_register 	gpio_reg 	(	
					.sys_clk(sys_clk),
					.sys_rst(sys_rst),
					.gpio_we(gpio_we),
					.gpio_addr(gpio_addr),
					.gpio_dat_i(gpio_dat_i),
					.gpio_dat_o(gpio_dat_o),
					.gpio_inta_o(gpio_inta_o),
					.aux_i(aux_i),
					.in_pad_i(in_pad_i),
					.gpio_eclk(ext_clk_to_gpio_eclk),
					.out_pad_o(out_pad_o),
					.oen_padoe_o(oen_padoe_o)
					);
							
					
	io_interface	io_intf		(
					.ext_clk_pad_i(ext_clk_pad_i),
					.out_pad_o(out_pad_o), 
					.oen_padoe_o(oen_padoe_o),
					.in_pad_i(in_pad_i),
					.io_pad(io_pad),
					.gpio_eclk(ext_clk_to_gpio_eclk)
					);
	
endmodule

tb/gpio_top_tb.v
module gpio_top_tb;
	
	reg pclk;
	reg preset;
	wire [31:0] prdata;
	reg [31:0] paddr;
	reg [31:0] pwdata;
	reg psel;
	reg penable;
	reg pwrite;
	reg [31:0] aux_in;
	wire irq;
	wire pready;
	wire [31:0] io_pad;
	reg ext_clk_pad_i;
	
	parameter addr_rgpio_in = 32'h00;
	parameter addr_rgpio_out = 32'h04;
	parameter addr_rgpio_oe = 32'h08;
	parameter addr_rgpio_inte = 32'h0c;
	parameter addr_rgpio_ptrig = 32'h10;
	parameter addr_rgpio_aux = 32'h14;
	parameter addr_rgpio_ctrl = 32'h18;
	parameter addr_rgpio_ints = 32'h1c;
	parameter addr_rgpio_eclk = 32'h20;
	parameter addr_rgpio_nec = 32'h24;
	
	parameter addr_rgpio_ctrl_inte = 0;
	parameter addr_rgpio_ctrl_ints = 1;
	
	gpio_top	DUT	(	
				pclk,
				preset,
				prdata,
				paddr,
				pwdata,
				psel,
				penable,
				pwrite,
				aux_in,
				irq,
				pready,
				io_pad,
				ext_clk_pad_i
				);
					
	initial
		pclk = 1'b0;
		
	always #5 pclk = ~pclk;
	
	initial
		ext_clk_pad_i = 1'b0;
	
	always #20 ext_clk_pad_i = ~ext_clk_pad_i;
	
	task reset;
	begin
		@(negedge pclk);
		preset = 1'b1;
		#10 preset = 1'b0;
	end
	endtask
	
	task initialize;
	begin
		@(negedge pclk);
		psel = 1'b0;
		pwrite = 1'b0;
		penable = 1'b0;
		paddr = 32'h0;
		pwdata = 32'h0;
		aux_in = 32'h0;
	end
	endtask
	
	task aux_write(input [31:0]in);
	begin
		@(negedge pclk);
		aux_in = in;
	end
	endtask
	
	task apb_write(input [31:0]addr, input [31:0]in);
	begin
		@(negedge pclk);
		paddr = addr;		//select phase
		psel = 1'b1;
		pwrite = 1'b1;
		penable = 1'b0;
		pwdata = in;
		
		@(negedge pclk);
		penable = 1'b1;		//enable phase
		
		@(negedge pclk);	
		penable = 1'b0;		//toggle penable
		
		@(negedge pclk);
		psel = 1'b0;
		pwrite = 1'b0;
		penable = 1'b0;		//reset all signal states
		
	end
	endtask
	
	task apb_read(input [31:0]addr);
	begin
		@(negedge pclk);
		paddr = addr;
		psel = 1'b1;
		pwrite = 1'b0;
		penable = 1'b0;		//select phase
		
		@(negedge pclk);
		penable = 1'b1;		//enable phase
		
		@(negedge pclk);
		penable = 1'b0;		//toggle penable
		
		@(negedge pclk);
		psel = 1'b0;
		pwrite = 1'b0;
		penable = 1'b0;		//reset all signal states
	end
	endtask
	
	reg io_dir = 1'b1;
	reg [31:0]temp_reg = 32'dz;
	
	task send_to_io_pad(input [31:0]input_iopad);
	begin
		io_dir = 1'b0;
		temp_reg = input_iopad;
	end
	endtask
	
	task set_io_pad_output;
		io_dir = 1'b1;
	endtask	
	
	assign io_pad = ~io_dir?temp_reg:32'dz;
	
	initial
	begin
		initialize;
		reset;
		#10;
		
		//gpio as output
		apb_write(addr_rgpio_inte, 32'h0);
		apb_write(addr_rgpio_out, 32'h5a5a_5a5a);
		apb_write(addr_rgpio_oe, 32'hffff_ffff);
		set_io_pad_output;
		
		//gpio as input, sys clk
		apb_write(addr_rgpio_oe, 32'h0);
		apb_write(addr_rgpio_ctrl, 2'd0);
		apb_write(addr_rgpio_inte, 32'h0);
		apb_write(addr_rgpio_eclk, 32'h0);
		send_to_io_pad(32'h8b8b_b8b8);
		apb_read(addr_rgpio_in);
		
		//gpio as aux input
		aux_write(32'hbbbb_dddd);
		apb_write(addr_rgpio_aux, 32'hffff_ffff);
		apb_write(addr_rgpio_oe, 32'hffff_ffff);
		set_io_pad_output;
		apb_write(addr_rgpio_aux, 32'd0);		//reset aux so we can pass values in upcoming tasks
		
		//gpio as bi-directional io in sys clk
		apb_write(addr_rgpio_inte, 32'd0);
		apb_write(addr_rgpio_eclk, 32'd0);
		apb_write(addr_rgpio_out, 32'h1020_3040);	//alternating nibbles for output
		apb_write(addr_rgpio_oe, 32'hf0f0_f0f0);	//making sure you are setting only those nibbles to be output
		send_to_io_pad(32'hzfzf_zfzf);			//alternating nibbles are for inputs
		apb_read(addr_rgpio_in);
		
		//gpio as input in interrupt mode in sys clk
		send_to_io_pad(32'h0000_ffff);
		apb_write(addr_rgpio_oe, 32'd0);
		apb_write(addr_rgpio_ctrl, 2'd1);
		apb_write(addr_rgpio_inte, 32'hffff_ffff);
		apb_write(addr_rgpio_ptrig, 32'hffff_0000);
		apb_write(addr_rgpio_eclk, 32'd0);
		send_to_io_pad(32'h87654321);
		apb_read(addr_rgpio_ctrl_ints);
		wait(irq);
		apb_read(addr_rgpio_in);
		
		//gpio as input, ext clk
		apb_write(addr_rgpio_oe, 32'h0);
		apb_write(addr_rgpio_ctrl, 2'd0);
		apb_write(addr_rgpio_inte, 32'h0);
		apb_write(addr_rgpio_nec, 32'h0000_f0f0);
		apb_write(addr_rgpio_eclk, 32'h0000_ffff);
		send_to_io_pad(32'h1234_5678);
		apb_read(addr_rgpio_in);
		
		//gpio as input in interrupt mode in ext clk
		apb_write(addr_rgpio_oe, 32'd0);
		apb_write(addr_rgpio_inte, 32'hffff_ffff);
		apb_write(addr_rgpio_ptrig, 32'hffff_0000);
		apb_write(addr_rgpio_ints, 32'h0);
		apb_write(addr_rgpio_ctrl, 2'd1);
		apb_write(addr_rgpio_nec, 32'h0000_f0f0);
		apb_write(addr_rgpio_eclk, 32'h0000_ffff);
		send_to_io_pad(32'h87654321);
		apb_read(addr_rgpio_ctrl_ints);
		wait(irq);
		apb_read(addr_rgpio_in);
		apb_write(addr_rgpio_ints, 32'h0);
		apb_write(addr_rgpio_ctrl, 2'd0);
		set_io_pad_output;
		
		//gpio as bi-directional io in ext clk
		apb_write(addr_rgpio_inte, 32'd0);
		apb_write(addr_rgpio_out, 32'h1020_3040);	//alternating nibbles for output
		apb_write(addr_rgpio_oe, 32'hf0f0_f0f0);	//making sure you are setting only those nibbles to be output
		apb_write(addr_rgpio_nec, 32'h0f0f_f0f0);
		apb_write(addr_rgpio_eclk, 32'h0f0f_0f0f);
		set_io_pad_output;
		send_to_io_pad(32'hzfzf_zfzf);			//alternating nibbles are for inputs
		apb_read(addr_rgpio_in);
		
		#200 $finish;
	end

	initial
	begin
        	$dumpfile("gpio_top.vcd");
        	$dumpvars(0, gpio_top_tb);
    	end

endmodule

sim/gpio_top.vcd
$date
	Thu Jun 11 18:12:05 2026
$end
$version
	Icarus Verilog
$end
$timescale
	1s
$end
$scope module gpio_top_tb $end
$var wire 32 ! io_pad [31:0] $end
$var wire 1 " pready $end
$var wire 32 # prdata [31:0] $end
$var wire 1 $ irq $end
$var reg 32 % aux_in [31:0] $end
$var reg 1 & ext_clk_pad_i $end
$var reg 1 ' io_dir $end
$var reg 32 ( paddr [31:0] $end
$var reg 1 ) pclk $end
$var reg 1 * penable $end
$var reg 1 + preset $end
$var reg 1 , psel $end
$var reg 32 - pwdata [31:0] $end
$var reg 1 . pwrite $end
$var reg 32 / temp_reg [31:0] $end
$scope module DUT $end
$var wire 32 0 aux_in [31:0] $end
$var wire 1 & ext_clk_pad_i $end
$var wire 32 1 io_pad [31:0] $end
$var wire 32 2 paddr [31:0] $end
$var wire 1 ) pclk $end
$var wire 1 * penable $end
$var wire 1 + preset $end
$var wire 1 , psel $end
$var wire 32 3 pwdata [31:0] $end
$var wire 1 . pwrite $end
$var wire 1 4 sys_rst $end
$var wire 1 5 sys_clk $end
$var wire 1 " pready $end
$var wire 32 6 prdata [31:0] $end
$var wire 32 7 out_pad_o [31:0] $end
$var wire 32 8 oen_padoe_o [31:0] $end
$var wire 1 $ irq $end
$var wire 32 9 in_pad_i [31:0] $end
$var wire 1 : gpio_we $end
$var wire 1 ; gpio_inta_o $end
$var wire 32 < gpio_dat_o [31:0] $end
$var wire 32 = gpio_dat_i [31:0] $end
$var wire 32 > gpio_addr [31:0] $end
$var wire 1 ? ext_clk_to_gpio_eclk $end
$var wire 32 @ aux_i [31:0] $end
$scope module aux_intf $end
$var wire 32 A aux_in [31:0] $end
$var wire 1 4 rst $end
$var wire 1 5 clk $end
$var reg 32 B aux_i [31:0] $end
$upscope $end
$scope module gpio_reg $end
$var wire 32 C aux_i [31:0] $end
$var wire 32 D extclk_in [31:0] $end
$var wire 32 E muxed_in [31:0] $end
$var wire 32 F out_pad_o [31:0] $end
$var wire 1 4 sys_rst $end
$var wire 1 5 sys_clk $end
$var wire 32 G oen_padoe_o [31:0] $end
$var wire 32 H in_pad_i [31:0] $end
$var wire 1 : gpio_we $end
$var wire 1 ; gpio_inta_o $end
$var wire 1 ? gpio_eclk $end
$var wire 32 I gpio_dat_i [31:0] $end
$var wire 32 J gpio_addr [31:0] $end
$var reg 32 K dat_reg [31:0] $end
$var reg 32 L gpio_dat_o [31:0] $end
$var reg 32 M nextc_sampled [31:0] $end
$var reg 32 N pextc_sampled [31:0] $end
$var reg 32 O rgpio_aux [31:0] $end
$var reg 2 P rgpio_ctrl [1:0] $end
$var reg 32 Q rgpio_eclk [31:0] $end
$var reg 32 R rgpio_in [31:0] $end
$var reg 32 S rgpio_inte [31:0] $end
$var reg 32 T rgpio_ints [31:0] $end
$var reg 32 U rgpio_nec [31:0] $end
$var reg 32 V rgpio_oe [31:0] $end
$var reg 32 W rgpio_out [31:0] $end
$var reg 32 X rgpio_ptrig [31:0] $end
$upscope $end
$scope module io_intf $end
$var wire 1 & ext_clk_pad_i $end
$var wire 1 ? gpio_eclk $end
$var wire 32 Y in_pad_i [31:0] $end
$var wire 32 Z io_pad [31:0] $end
$var wire 32 [ oen_padoe_o [31:0] $end
$var wire 32 \ out_pad_o [31:0] $end
$scope begin gpio_output_tri_buffers[0] $end
$upscope $end
$scope begin gpio_output_tri_buffers[1] $end
$upscope $end
$scope begin gpio_output_tri_buffers[2] $end
$upscope $end
$scope begin gpio_output_tri_buffers[3] $end
$upscope $end
$scope begin gpio_output_tri_buffers[4] $end
$upscope $end
$scope begin gpio_output_tri_buffers[5] $end
$upscope $end
$scope begin gpio_output_tri_buffers[6] $end
$upscope $end
$scope begin gpio_output_tri_buffers[7] $end
$upscope $end
$scope begin gpio_output_tri_buffers[8] $end
$upscope $end
$scope begin gpio_output_tri_buffers[9] $end
$upscope $end
$scope begin gpio_output_tri_buffers[10] $end
$upscope $end
$scope begin gpio_output_tri_buffers[11] $end
$upscope $end
$scope begin gpio_output_tri_buffers[12] $end
$upscope $end
$scope begin gpio_output_tri_buffers[13] $end
$upscope $end
$scope begin gpio_output_tri_buffers[14] $end
$upscope $end
$scope begin gpio_output_tri_buffers[15] $end
$upscope $end
$scope begin gpio_output_tri_buffers[16] $end
$upscope $end
$scope begin gpio_output_tri_buffers[17] $end
$upscope $end
$scope begin gpio_output_tri_buffers[18] $end
$upscope $end
$scope begin gpio_output_tri_buffers[19] $end
$upscope $end
$scope begin gpio_output_tri_buffers[20] $end
$upscope $end
$scope begin gpio_output_tri_buffers[21] $end
$upscope $end
$scope begin gpio_output_tri_buffers[22] $end
$upscope $end
$scope begin gpio_output_tri_buffers[23] $end
$upscope $end
$scope begin gpio_output_tri_buffers[24] $end
$upscope $end
$scope begin gpio_output_tri_buffers[25] $end
$upscope $end
$scope begin gpio_output_tri_buffers[26] $end
$upscope $end
$scope begin gpio_output_tri_buffers[27] $end
$upscope $end
$scope begin gpio_output_tri_buffers[28] $end
$upscope $end
$scope begin gpio_output_tri_buffers[29] $end
$upscope $end
$scope begin gpio_output_tri_buffers[30] $end
$upscope $end
$scope begin gpio_output_tri_buffers[31] $end
$upscope $end
$upscope $end
$scope module slv_intf $end
$var wire 32 ] gpio_addr [31:0] $end
$var wire 32 ^ gpio_dat_o [31:0] $end
$var wire 1 ; gpio_inta_o $end
$var wire 1 $ irq $end
$var wire 32 _ paddr [31:0] $end
$var wire 1 ) pclk $end
$var wire 1 * penable $end
$var wire 1 + preset $end
$var wire 1 , psel $end
$var wire 32 ` pwdata [31:0] $end
$var wire 1 . pwrite $end
$var wire 1 5 sys_clk $end
$var wire 1 4 sys_rst $end
$var wire 1 " pready $end
$var reg 32 a gpio_dat_i [31:0] $end
$var reg 1 : gpio_we $end
$var reg 2 b next [1:0] $end
$var reg 32 c prdata [31:0] $end
$var reg 2 d pres [1:0] $end
$upscope $end
$upscope $end
$scope task apb_read $end
$var reg 32 e addr [31:0] $end
$upscope $end
$scope task apb_write $end
$var reg 32 f addr [31:0] $end
$var reg 32 g in [31:0] $end
$upscope $end
$scope task aux_write $end
$var reg 32 h in [31:0] $end
$upscope $end
$scope task initialize $end
$upscope $end
$scope task reset $end
$upscope $end
$scope task send_to_io_pad $end
$var reg 32 i input_iopad [31:0] $end
$upscope $end
$scope task set_io_pad_output $end
$upscope $end
$upscope $end
$enddefinitions $end
#0
$dumpvars
bx i
bx h
bx g
bx f
bx e
bx d
bx c
bx b
bx a
bx `
bx _
bx ^
bx ]
bx \
bx [
bx Z
bx Y
bx X
bx W
bx V
bx U
bx T
bx S
bx R
bx Q
bx P
bx O
bx N
bx M
bx L
bx K
bx J
bx I
bx H
bx G
bx F
bx E
bx D
bx C
bx B
bx A
bx @
0?
bx >
bx =
bx <
x;
x:
bx 9
bx 8
bx 7
bx 6
05
x4
bx 3
bx 2
bx 1
bx 0
bz /
x.
bx -
x,
x+
x*
0)
bx (
1'
0&
bx %
x$
bx #
x"
bx !
$end
#5
15
1)
#10
b0 #
b0 6
b0 c
0:
b0 =
b0 I
b0 a
b0 b
b0 %
b0 0
b0 A
b0 -
b0 3
b0 `
b0 >
b0 J
b0 ]
b0 (
b0 2
b0 _
0*
0.
0,
05
0)
#15
b0 @
b0 B
b0 C
b0 d
15
1)
#20
b0 7
b0 F
b0 \
bz 9
bz H
bz Y
bz !
bz 1
bz Z
b0 D
b0 K
0$
0;
b0 P
b0 W
b0 8
b0 G
b0 V
b0 [
b0 S
b0 X
b0 O
b0 Q
b0 U
b0 R
b0 <
b0 L
b0 ^
b0 T
b0 M
b0 N
1"
14
1+
05
0)
1?
1&
#25
15
1)
#30
0"
05
0)
04
0+
#35
bx K
bx R
15
1)
#40
bz M
b1 b
b0 K
1.
1,
b1100 >
b1100 J
b1100 ]
b1100 (
b1100 2
b1100 _
05
0)
b0 g
b1100 f
0?
0&
#45
b1 d
15
1)
#50
b10 b
1*
05
0)
#55
1"
1:
b1 b
b10 d
15
1)
#60
bx D
bz N
0*
05
0)
1?
1&
#65
0"
0:
b1 d
15
1)
#70
b0 b
b1011010010110100101101001011010 g
b100 f
0.
0,
05
0)
#75
b0 d
15
1)
#80
b1 b
b1011010010110100101101001011010 -
b1011010010110100101101001011010 3
b1011010010110100101101001011010 `
1.
1,
b100 >
b100 J
b100 ]
b100 (
b100 2
b100 _
05
0)
0?
0&
#85
b1 d
15
1)
#90
b10 b
1*
05
0)
#95
1"
1:
b1011010010110100101101001011010 =
b1011010010110100101101001011010 I
b1011010010110100101101001011010 a
b1 b
b10 d
15
1)
#100
0*
05
0)
1?
1&
#105
b1011010010110100101101001011010 7
b1011010010110100101101001011010 F
b1011010010110100101101001011010 \
0"
b1011010010110100101101001011010 K
0:
b0 =
b0 I
b0 a
b1011010010110100101101001011010 W
b1 d
15
1)
#110
b0 b
b11111111111111111111111111111111 g
b1000 f
0.
0,
05
0)
#115
b1011010010110100101101001011010 <
b1011010010110100101101001011010 L
b1011010010110100101101001011010 ^
b0 d
15
1)
#120
b1 b
b0 K
b11111111111111111111111111111111 -
b11111111111111111111111111111111 3
b11111111111111111111111111111111 `
1.
1,
b1000 >
b1000 J
b1000 ]
b1000 (
b1000 2
b1000 _
05
0)
0?
0&
#125
b0 <
b0 L
b0 ^
b1 d
15
1)
#130
b10 b
1*
05
0)
#135
1"
1:
b11111111111111111111111111111111 =
b11111111111111111111111111111111 I
b11111111111111111111111111111111 a
b1 b
b10 d
15
1)
#140
0*
05
0)
1?
1&
#145
b1011010010110100101101001011010 E
b1011010010110100101101001011010 9
b1011010010110100101101001011010 H
b1011010010110100101101001011010 Y
b1011010010110100101101001011010 !
b1011010010110100101101001011010 1
b1011010010110100101101001011010 Z
0"
b11111111111111111111111111111111 K
0:
b0 =
b0 I
b0 a
b11111111111111111111111111111111 8
b11111111111111111111111111111111 G
b11111111111111111111111111111111 V
b11111111111111111111111111111111 [
b1 d
15
1)
#150
b0 b
b0 g
0.
0,
05
0)
#155
b1011010010110100101101001011010 R
b11111111111111111111111111111111 <
b11111111111111111111111111111111 L
b11111111111111111111111111111111 ^
b0 d
15
1)
#160
b1011010010110100101101001011010 M
b1 b
b0 -
b0 3
b0 `
1.
1,
05
0)
0?
0&
#165
b1 d
15
1)
#170
b10 b
1*
05
0)
#175
1"
1:
b1 b
b10 d
15
1)
#180
b1011010010110100101101001011010 D
b1011010010110100101101001011010 N
0*
05
0)
1?
1&
#185
bx E
bz 9
bz H
bz Y
bz !
bz 1
bz Z
0"
b0 K
0:
b0 8
b0 G
b0 V
b0 [
b1 d
15
1)
#190
b0 b
b11000 f
0.
0,
05
0)
#195
bx R
b0 <
b0 L
b0 ^
b0 d
15
1)
#200
bz M
b1 b
1.
1,
b11000 >
b11000 J
b11000 ]
b11000 (
b11000 2
b11000 _
05
0)
0?
0&
#205
b1 d
15
1)
#210
b10 b
1*
05
0)
#215
1"
1:
b1 b
b10 d
15
1)
#220
bx D
bz N
0*
05
0)
1?
1&
#225
0"
0:
b1 d
15
1)
#230
b0 b
b1100 f
0.
0,
05
0)
#235
b0 d
15
1)
#240
b1 b
1.
1,
b1100 >
b1100 J
b1100 ]
b1100 (
b1100 2
b1100 _
05
0)
0?
0&
#245
b1 d
15
1)
#250
b10 b
1*
05
0)
#255
1"
1:
b1 b
b10 d
15
1)
#260
0*
05
0)
1?
1&
#265
0"
0:
b1 d
15
1)
#270
b0 b
b100000 f
0.
0,
05
0)
#275
b0 d
15
1)
