rtl/gpio_register.v
module gpio_register (	input sys_clk,
			input sys_rst,
			input gpio_we,
			input [31:0] gpio_addr,
			input [31:0] gpio_dat_i,
			output reg [31:0] gpio_dat_o,
			output gpio_inta_o,
			input [31:0] aux_i,
			input [31:0] in_pad_i,
			input gpio_eclk,
			output [31:0] out_pad_o,
			output [31:0] oen_padoe_o
			);

	
	parameter addr_rgpio_in = 32'h00;
	parameter addr_rgpio_out = 32'h04;
	parameter addr_rgpio_oe = 32'h08;
	parameter addr_rgpio_inte = 32'h0c;
	parameter addr_rgpio_ptrig = 32'h10;
	parameter addr_rgpio_aux = 32'h14;
	parameter addr_rgpio_ctrl = 32'h18;
	parameter addr_rgpio_ints = 32'h1c;
	parameter addr_rgpio_eclk = 32'h20;
	parameter addr_rgpio_nec = 32'h24;
	
	parameter addr_rgpio_ctrl_inte = 0;
	parameter addr_rgpio_ctrl_ints = 1;
	
	reg [31:0] rgpio_in, rgpio_out, rgpio_oe, rgpio_inte, rgpio_ptrig, rgpio_aux, rgpio_ctrl, rgpio_ints, rgpio_eclk, rgpio_nec;
	reg [1:0]  rgpio_ctrl;
	
	reg [31:0] dat_reg;				//used to hold output, we use this to send to gpio_dat_o reg on posedge of sys clk
	
	wire [31:0] extclk_in;				//multiplexed inputs by ext clk
	reg [31:0] pextc_sampled, nextc_sampled;	//posedge and negedge ext clk sampled inputs
	
	//--------------------------------------
	
	//gpio ctrl logic block
	
	always @ (posedge sys_clk or posedge sys_rst)
		if(sys_rst == 1'b1)
			rgpio_ctrl <= 2'd0;
		else if( (gpio_addr == addr_rgpio_ctrl) && gpio_we == 1'b1 )					//if addr is of gpio ctrl reg and wr en is high
			rgpio_ctrl <= gpio_dat_i[1:0];								//assign lsb 2 bits of input stream to ctrl reg
		else if(rgpio_ctrl[addr_rgpio_ctrl_inte] == 1'b1)						//if interrupts enabled
			rgpio_ctrl[addr_rgpio_ctrl_ints] <= rgpio_ctrl[addr_rgpio_ctrl_ints] | gpio_inta_o;	//update status reg and keep it high until serviced
	
	//--------------------------------------
	
	//gpio out logic block
	
	always @ (posedge sys_clk or posedge sys_rst)
		if(sys_rst == 1'b1)
			rgpio_out <= 32'd0;
		else if( (gpio_addr == addr_rgpio_out) && gpio_we == 1'b1 )
			rgpio_out <= gpio_dat_i[31:0];
		else
			rgpio_out <= rgpio_out;
			
	//--------------------------------------
	
	//gpio output enable logic block
	
	always @ (posedge sys_clk or posedge sys_rst)
		if(sys_rst == 1'b1)
			rgpio_oe <= 32'd0;
		else if( (gpio_addr == addr_rgpio_oe) && gpio_we == 1'b1 )
			rgpio_oe <= gpio_dat_i[31:0];
		else
			rgpio_oe <= rgpio_oe;		//extra line added, if bug remove
			
	//--------------------------------------
	
	//gpio interrupt enable
	
	always @ (posedge sys_clk or posedge sys_rst)
		if(sys_rst == 1'b1)
			rgpio_inte <= 32'd0;
		else if( (gpio_addr == addr_rgpio_inte) && gpio_we == 1'b1 )
			rgpio_inte <= gpio_dat_i[31:0];
		else
			rgpio_inte <= rgpio_inte;
	
	//--------------------------------------
	
	//gpio posedge trigger register
	
	always @ (posedge sys_clk or posedge sys_rst)
		if(sys_rst == 1'b1)
			rgpio_ptrig <= 32'd0;
		else if( (gpio_addr == addr_rgpio_ptrig) && gpio_we == 1'b1 )
			rgpio_ptrig <= gpio_dat_i[31:0];
		else
			rgpio_ptrig <= rgpio_ptrig;
		
	//--------------------------------------
	
	//gpio aux register
	
	always @ (posedge sys_clk or posedge sys_rst)
		if(sys_rst == 1'b1)
			rgpio_aux <= 32'd0;
		else if( (gpio_addr == addr_rgpio_aux) && gpio_we == 1'b1 )
			rgpio_aux <= gpio_dat_i[31:0];
		else
			rgpio_aux <= rgpio_aux;
			
	//--------------------------------------
	
	//gpio ext clk register
	
	always @ (posedge sys_clk or posedge sys_rst)
		if(sys_rst == 1'b1)
			rgpio_eclk <= 32'd0;
		else if( (gpio_addr == addr_rgpio_eclk) && gpio_we == 1'b1 )
			rgpio_eclk <= gpio_dat_i[31:0];
		else
			rgpio_eclk <= rgpio_eclk;
		
	//--------------------------------------
	
	//neg edge ext clk register
	
	always @ (posedge sys_clk or posedge sys_rst)
		if(sys_rst == 1'b1)
			rgpio_nec <= 32'd0;
		else if( (gpio_addr == addr_rgpio_nec) && gpio_we == 1'b1)
			rgpio_nec <= gpio_dat_i[31:0];
		else
			rgpio_nec <= rgpio_nec;
			
	//--------------------------------------
	
	//sending input to gpio in reg
	
	wire [31:0] muxed_in;
	
	always @ (posedge sys_clk or posedge sys_rst)
		if(sys_rst == 1'b1)
			rgpio_in <= 32'd0;
		else
			rgpio_in <= muxed_in;
	
	assign muxed_in = (rgpio_eclk & extclk_in) | (~rgpio_eclk & in_pad_i);		//if ext clk reg high, then pass ext clk, if not, pass input from input pad
	
	assign extclk_in = (~rgpio_nec & pextc_sampled) | (rgpio_nec & nextc_sampled);	//if neg edge reg low, then pass posedge sampled input, if high, then pass negedge sampled input
	
	//--------------------------------------
	
	//posedge sampled input, note the use of ext clk here
	
	always @ (posedge gpio_eclk or posedge sys_rst)
		if(sys_rst == 1'b1)
			pextc_sampled <= 32'd0;
		else
			pextc_sampled <= in_pad_i;
	
	//negedge sampled input, note ext clk
	
	always @ (negedge gpio_eclk or posedge sys_rst)
		if(sys_rst == 1'b1)
			nextc_sampled <= 32'd0;
		else
			nextc_sampled <= in_pad_i;
	
	//--------------------------------------
	
	//passing register contents to intermediate signal
	
	always @ (*)
		case(gpio_addr)
			addr_rgpio_out: dat_reg = rgpio_out;
			addr_rgpio_oe: dat_reg = rgpio_oe;
			addr_rgpio_inte: dat_reg = rgpio_inte;
			addr_rgpio_ptrig: dat_reg = rgpio_ptrig;
			addr_rgpio_nec: dat_reg = rgpio_nec;
			addr_rgpio_eclk: dat_reg = rgpio_eclk;
			addr_rgpio_aux: dat_reg = rgpio_aux;
			addr_rgpio_ctrl:	begin
							dat_reg[1:0] = rgpio_ctrl;
							dat_reg[31:2] = 30'd0;
						end
			addr_rgpio_ints: dat_reg = rgpio_ints;
			default: dat_reg = rgpio_in;
		endcase
		
	//--------------------------------------
	
	//passing intermediate signal value to gpio output reg
	
	always @ (posedge sys_clk or posedge sys_rst)
		if(sys_rst == 1'b1)
			gpio_dat_o <= 32'd0;
		else
			gpio_dat_o <= dat_reg;

	//--------------------------------------
	
	//gpio interrupt status reg, wr and rd 
	
	always @ (posedge sys_clk or posedge sys_rst)
		if(sys_rst == 1'b1)
			rgpio_ints <= 32'd0;
		else if( (gpio_addr == addr_rgpio_ints) && gpio_we == 1'b1 )
			rgpio_ints <= gpio_dat_i;
		else if(rgpio_ctrl[addr_rgpio_ctrl_inte] == 1'b1)
			rgpio_ints <= (rgpio_ints | ((muxed_in ^ rgpio_in) & ~(muxed_in ^ rgpio_ptrig)) & rgpio_inte);
	
	//--------------------------------------
	
	assign gpio_inta_o = |rgpio_ints ? rgpio_ctrl[addr_rgpio_ctrl_inte] : 1'b0;		//gen interrupt req, note the use of the 'reduction or'	operator
	assign oen_padoe_o = rgpio_oe;								//output enables are the same as gpio output enable register bits
	assign out_pad_o = (rgpio_out & ~rgpio_aux) | (aux_i & rgpio_aux);			//generate gpio output as register output if no aux input, if aux input present, pass that as output
	
endmodule

tb/gpio_register_tb.v
`timescale 1ns/1ps

module gpio_register_tb;

    reg sys_clk;
    reg sys_rst;
    reg gpio_we;
    reg [31:0] gpio_addr;
    reg [31:0] gpio_dat_i;
    reg [31:0] aux_i;
    reg [31:0] in_pad_i;
    reg gpio_eclk;

    wire [31:0] gpio_dat_o;
    wire gpio_inta_o;
    wire [31:0] out_pad_o;
    wire [31:0] oen_padoe_o;
	
    gpio_register DUT (
			.sys_clk(sys_clk),
			.sys_rst(sys_rst),
			.gpio_we(gpio_we),
			.gpio_addr(gpio_addr),
			.gpio_dat_i(gpio_dat_i),
			.gpio_dat_o(gpio_dat_o),
			.gpio_inta_o(gpio_inta_o),
			.aux_i(aux_i),
			.in_pad_i(in_pad_i),
			.gpio_eclk(gpio_eclk),
			.out_pad_o(out_pad_o),
			.oen_padoe_o(oen_padoe_o)
			);

    initial sys_clk = 1'b0;
    always #5 sys_clk = ~sys_clk;
    
    initial gpio_eclk = 1'b0;
    always #20 gpio_eclk = ~gpio_eclk;

    initial 
    begin
	//resetting register module
        sys_rst     = 1'b1;
        gpio_we     = 1'b0;
        gpio_addr   = 32'h0;
        gpio_dat_i  = 32'h0;
        aux_i       = 32'h0;
        in_pad_i    = 32'hABABABAB; 		//input to test default case
        gpio_eclk   = 1'b0;
        
        #15;
        sys_rst     = 1'b0; 			//release reset
	@(negedge sys_clk);			//wait a cycle

        //basic writing operation test
        gpio_addr  = 32'h08; 			//select the output enable register
        gpio_dat_i = 32'hFFFF_FFFF;		//enable all lines
	gpio_we    = 1'b1;			//enable writing 
        
	@(negedge sys_clk);			//wait a cycle
        
		
        gpio_addr  = 32'h04;			//select gpio out register
        gpio_dat_i = 32'h1234_5678;		//write a value
        
        @(negedge sys_clk);				
		
	//reading output register contents
        gpio_addr  = 32'h04;			//still the same gpio out register
        gpio_we    = 1'b0; 			//turn off write enable for reading from output reg
		
        @(negedge sys_clk); 
        @(negedge sys_clk); 			//2 clk cycles, 1 to latch to dat_reg, another to send to output register
        
        // default case testing
        gpio_addr  = 32'h99; 			//random address to force case statement to default
        
        @(negedge sys_clk);
        @(negedge sys_clk); 			//2 cycle delay to let data be output

        //aux input testing
        aux_i      = 32'hAAAA_BBBB;		//random value to pass as aux input
        gpio_addr  = 32'h14;			//select aux register
        gpio_dat_i = 32'hFFFF_FFFF; 		//select aux line for all pins
        gpio_we    = 1'b1;				
        
        @(negedge sys_clk);
        gpio_we    = 1'b0;			//pull down to enable reading
        
        #40;
        $finish;
    end

    initial 
    begin
        $dumpfile("gpio_sim.vcd");
        $dumpvars(0, gpio_register_tb);
    end

endmodule

sim/gpio_sim.vcd
$date
	Wed May 27 18:56:28 2026
$end
$version
	Icarus Verilog
$end
$timescale
	1ps
$end
$scope module gpio_register_tb $end
$var wire 32 ! out_pad_o [31:0] $end
$var wire 32 " oen_padoe_o [31:0] $end
$var wire 1 # gpio_inta_o $end
$var wire 32 $ gpio_dat_o [31:0] $end
$var reg 32 % aux_i [31:0] $end
$var reg 32 & gpio_addr [31:0] $end
$var reg 32 ' gpio_dat_i [31:0] $end
$var reg 1 ( gpio_eclk $end
$var reg 1 ) gpio_we $end
$var reg 32 * in_pad_i [31:0] $end
$var reg 1 + sys_clk $end
$var reg 1 , sys_rst $end
$scope module DUT $end
$var wire 32 - aux_i [31:0] $end
$var wire 32 . extclk_in [31:0] $end
$var wire 32 / gpio_addr [31:0] $end
$var wire 32 0 gpio_dat_i [31:0] $end
$var wire 1 ( gpio_eclk $end
$var wire 1 ) gpio_we $end
$var wire 32 1 in_pad_i [31:0] $end
$var wire 32 2 muxed_in [31:0] $end
$var wire 32 3 oen_padoe_o [31:0] $end
$var wire 32 4 out_pad_o [31:0] $end
$var wire 1 + sys_clk $end
$var wire 1 , sys_rst $end
$var wire 1 # gpio_inta_o $end
$var reg 32 5 dat_reg [31:0] $end
$var reg 32 6 gpio_dat_o [31:0] $end
$var reg 32 7 nextc_sampled [31:0] $end
$var reg 32 8 pextc_sampled [31:0] $end
$var reg 32 9 rgpio_aux [31:0] $end
$var reg 2 : rgpio_ctrl [1:0] $end
$var reg 32 ; rgpio_eclk [31:0] $end
$var reg 32 < rgpio_in [31:0] $end
$var reg 32 = rgpio_inte [31:0] $end
$var reg 32 > rgpio_ints [31:0] $end
$var reg 32 ? rgpio_nec [31:0] $end
$var reg 32 @ rgpio_oe [31:0] $end
$var reg 32 A rgpio_out [31:0] $end
$var reg 32 B rgpio_ptrig [31:0] $end
$upscope $end
$upscope $end
$enddefinitions $end
#0
$dumpvars
b0 B
b0 A
b0 @
b0 ?
b0 >
b0 =
b0 <
b0 ;
b0 :
b0 9
b0 8
b0 7
b0 6
b0 5
b0 4
b0 3
b10101011101010111010101110101011 2
b10101011101010111010101110101011 1
b0 0
b0 /
b0 .
b0 -
1,
0+
b10101011101010111010101110101011 *
0)
0(
b0 '
b0 &
b0 %
b0 $
0#
b0 "
b0 !
$end
#5000
1+
#10000
0+
#15000
b10101011101010111010101110101011 5
b10101011101010111010101110101011 <
1+
0,
#20000
b10101011101010111010101110101011 .
b10101011101010111010101110101011 8
b0 5
1)
b11111111111111111111111111111111 '
b11111111111111111111111111111111 0
b1000 &
b1000 /
0+
1(
#25000
b11111111111111111111111111111111 5
b11111111111111111111111111111111 "
b11111111111111111111111111111111 3
b11111111111111111111111111111111 @
1+
#30000
b0 5
b10010001101000101011001111000 '
b10010001101000101011001111000 0
b100 &
b100 /
0+
#35000
b10010001101000101011001111000 !
b10010001101000101011001111000 4
b10010001101000101011001111000 5
b10010001101000101011001111000 A
1+
#40000
b10101011101010111010101110101011 7
0)
0+
0(
#45000
b10010001101000101011001111000 $
b10010001101000101011001111000 6
1+
#50000
0+
#55000
1+
#60000
b10101011101010111010101110101011 5
b10011001 &
b10011001 /
0+
1(
#65000
b10101011101010111010101110101011 $
b10101011101010111010101110101011 6
1+
#70000
0+
#75000
1+
#80000
b0 5
1)
b11111111111111111111111111111111 '
b11111111111111111111111111111111 0
b10100 &
b10100 /
b10101010101010101011101110111011 %
b10101010101010101011101110111011 -
0+
0(
#85000
b10101010101010101011101110111011 !
b10101010101010101011101110111011 4
b11111111111111111111111111111111 5
b0 $
b0 6
b11111111111111111111111111111111 9
1+
#90000
0)
0+
#95000
b11111111111111111111111111111111 $
b11111111111111111111111111111111 6
1+
